pen_writer/__init__.py
pen_writer/main.py
pen_writer-0.3.1.dist-info/METADATA
pen_writer-0.3.1.dist-info/WHEEL
pen_writer-0.3.1.dist-info/entry_points.txt
pen_writer-0.3.1.dist-info/RECORD
