Metadata-Version: 2.1
Name: pen-writer
Version: 0.3.1
Summary: Writing tool for Astro.js blogs
License: MIT
Author: Sam Newby
Requires-Python: >=3.11,<4.0
Classifier: License :: OSI Approved :: MIT License
Classifier: Programming Language :: Python :: 3
Classifier: Programming Language :: Python :: 3.11
Requires-Dist: fastapi[all] (>=0.100.1,<0.101.0)
Requires-Dist: pygithub (>=1.59.0,<2.0.0)
Requires-Dist: typer[all] (>=0.9.0,<0.10.0)
